[
  {
    "jan_code": "4210201443391",
    "product_name": "BRAUN ブラウン シリーズ9 Pro 9465cc-V",
    "current_price": 32350,
    "previous_price": 39800.0,
    "price_change_rate": -18.718592964824122,
    "current_availability": "在庫あり",
    "previous_availability": "在庫あり",
    "shop_name": "RUSION　楽天市場店",
    "item_url": "https://hb.afl.rakuten.co.jp/hgc/g00tsj3j.f7sleae8.g00tsj3j.f7slfe68/?pc=https%3A%2F%2Fitem.rakuten.co.jp%2Frusion%2Fsdth_4210201443391%2F&m=http%3A%2F%2Fm.rakuten.co.jp%2Frusion%2Fi%2F10005845%2F&rafcid=wsc_i_is_1027811366364555365",
    "affiliate_url": "https://hb.afl.rakuten.co.jp/hgc/g00tsj3j.f7sleae8.g00tsj3j.f7slfe68/?pc=https%3A%2F%2Fitem.rakuten.co.jp%2Frusion%2Fsdth_4210201443391%2F&m=http%3A%2F%2Fm.rakuten.co.jp%2Frusion%2Fi%2F10005845%2F&rafcid=wsc_i_is_1027811366364555365",
    "timestamp": "2025-08-25 09:04:45"
  },
  {
    "jan_code": "4549046134981",
    "product_name": "【ほぼ新品・本体のみ】SONY Xperia Ace III A203SO ブルー ワイモバイル 【日曜日以外即日発送】【送料無料】",
    "current_price": 13700,
    "previous_price": 14799.0,
    "price_change_rate": -7.426177444421921,
    "current_availability": "在庫あり",
    "previous_availability": "在庫あり",
    "shop_name": "モバイル販売",
    "item_url": "https://hb.afl.rakuten.co.jp/hgc/g00tfghj.f7sle2be.g00tfghj.f7slf2d8/?pc=https%3A%2F%2Fitem.rakuten.co.jp%2Fmobileshop1%2Fz549046134981%2F&m=http%3A%2F%2Fm.rakuten.co.jp%2Fmobileshop1%2Fi%2F10007430%2F&rafcid=wsc_i_is_1027811366364555365",
    "affiliate_url": "https://hb.afl.rakuten.co.jp/hgc/g00tfghj.f7sle2be.g00tfghj.f7slf2d8/?pc=https%3A%2F%2Fitem.rakuten.co.jp%2Fmobileshop1%2Fz549046134981%2F&m=http%3A%2F%2Fm.rakuten.co.jp%2Fmobileshop1%2Fi%2F10007430%2F&rafcid=wsc_i_is_1027811366364555365",
    "timestamp": "2025-08-25 09:11:08"
  },
  {
    "jan_code": "4549212304378",
    "product_name": "【あす楽関東_対応】RICOH（リコー）WG-80 ブラック約1600万画素 本格防水、耐衝撃、防塵、耐寒 デジタルカメラ[4549212304378]",
    "current_price": 41978,
    "previous_price": 49140.0,
    "price_change_rate": -14.574684574684573,
    "current_availability": "在庫あり",
    "previous_availability": "在庫あり",
    "shop_name": "on HOME-オンホーム-",
    "item_url": "https://hb.afl.rakuten.co.jp/hgc/g00pwlgj.f7sle1dd.g00pwlgj.f7slfdf6/?pc=https%3A%2F%2Fitem.rakuten.co.jp%2Fonhome%2F176574%2F&m=http%3A%2F%2Fm.rakuten.co.jp%2Fonhome%2Fi%2F10064261%2F&rafcid=wsc_i_is_1027811366364555365",
    "affiliate_url": "https://hb.afl.rakuten.co.jp/hgc/g00pwlgj.f7sle1dd.g00pwlgj.f7slfdf6/?pc=https%3A%2F%2Fitem.rakuten.co.jp%2Fonhome%2F176574%2F&m=http%3A%2F%2Fm.rakuten.co.jp%2Fonhome%2Fi%2F10064261%2F&rafcid=wsc_i_is_1027811366364555365",
    "timestamp": "2025-08-25 09:13:21"
  },
  {
    "jan_code": "4549550273978",
    "product_name": "まごころ長期修理保証(保証5年)［加入料：対象商品代金の5%］商品「ELD-HTV060UBK」専用加入料(※加入料のみ注文不可)",
    "current_price": 979,
    "previous_price": 21237.0,
    "price_change_rate": -95.3901210152093,
    "current_availability": "在庫あり",
    "previous_availability": "在庫あり",
    "shop_name": "Joshin web 家電とPCの大型専門店",
    "item_url": "https://hb.afl.rakuten.co.jp/hgc/g00pukwj.f7sled54.g00pukwj.f7slfea6/?pc=https%3A%2F%2Fitem.rakuten.co.jp%2Fjism%2F4549550273978-44-23422-n-w3%2F&m=http%3A%2F%2Fm.rakuten.co.jp%2Fjism%2Fi%2F14431701%2F&rafcid=wsc_i_is_1027811366364555365",
    "affiliate_url": "https://hb.afl.rakuten.co.jp/hgc/g00pukwj.f7sled54.g00pukwj.f7slfea6/?pc=https%3A%2F%2Fitem.rakuten.co.jp%2Fjism%2F4549550273978-44-23422-n-w3%2F&m=http%3A%2F%2Fm.rakuten.co.jp%2Fjism%2Fi%2F14431701%2F&rafcid=wsc_i_is_1027811366364555365",
    "timestamp": "2025-08-25 09:15:22"
  },
  {
    "jan_code": "4549980651988",
    "product_name": "【お得・新品・送料無料・即納】パナソニック｜Panasonic デジタルコードレス普通紙ファクス KX-PD350DL-W ※外箱傷あり（倉庫移動中に箱傷み）",
    "current_price": 23153,
    "previous_price": 33250.0,
    "price_change_rate": -30.36691729323308,
    "current_availability": "在庫あり",
    "previous_availability": "在庫あり",
    "shop_name": "らいぶshop",
    "item_url": "https://hb.afl.rakuten.co.jp/hgc/g00r1fdj.f7sle73b.g00r1fdj.f7slf83a/?pc=https%3A%2F%2Fitem.rakuten.co.jp%2Flcs-live%2F10012738%2F&m=http%3A%2F%2Fm.rakuten.co.jp%2Flcs-live%2Fi%2F10012738%2F&rafcid=wsc_i_is_1027811366364555365",
    "affiliate_url": "https://hb.afl.rakuten.co.jp/hgc/g00r1fdj.f7sle73b.g00r1fdj.f7slf83a/?pc=https%3A%2F%2Fitem.rakuten.co.jp%2Flcs-live%2F10012738%2F&m=http%3A%2F%2Fm.rakuten.co.jp%2Flcs-live%2Fi%2F10012738%2F&rafcid=wsc_i_is_1027811366364555365",
    "timestamp": "2025-08-25 09:21:27"
  },
  {
    "jan_code": "4549980746424",
    "product_name": "パナソニック ドライヤー イオニティ 速乾 大風量 パワフルドライ 低温モード ダブルミネラルイオン ダークグレー EH-NE7L-H",
    "current_price": 13118,
    "previous_price": 14592.0,
    "price_change_rate": -10.101425438596491,
    "current_availability": "在庫あり",
    "previous_availability": "在庫あり",
    "shop_name": "kokolohasstyle",
    "item_url": "https://hb.afl.rakuten.co.jp/hgc/g00u3xuj.f7slef54.g00u3xuj.f7slf7ae/?pc=https%3A%2F%2Fitem.rakuten.co.jp%2Fkokolohas-style%2F202312020216234549980746424%2F&m=http%3A%2F%2Fm.rakuten.co.jp%2Fkokolohas-style%2Fi%2F10053741%2F&rafcid=wsc_i_is_1027811366364555365",
    "affiliate_url": "https://hb.afl.rakuten.co.jp/hgc/g00u3xuj.f7slef54.g00u3xuj.f7slf7ae/?pc=https%3A%2F%2Fitem.rakuten.co.jp%2Fkokolohas-style%2F202312020216234549980746424%2F&m=http%3A%2F%2Fm.rakuten.co.jp%2Fkokolohas-style%2Fi%2F10053741%2F&rafcid=wsc_i_is_1027811366364555365",
    "timestamp": "2025-08-25 09:23:01"
  },
  {
    "jan_code": "4942857239133",
    "product_name": "arrows We2 F-52E docomo [ライトオレンジ]　SIMフリー　白ロム",
    "current_price": 16976,
    "previous_price": 18980.0,
    "price_change_rate": -10.558482613277134,
    "current_availability": "在庫あり",
    "previous_availability": "在庫あり",
    "shop_name": "らいぶshop",
    "item_url": "https://hb.afl.rakuten.co.jp/hgc/g00r1fdj.f7sle73b.g00r1fdj.f7slf83a/?pc=https%3A%2F%2Fitem.rakuten.co.jp%2Flcs-live%2F10016929%2F&m=http%3A%2F%2Fm.rakuten.co.jp%2Flcs-live%2Fi%2F10016842%2F&rafcid=wsc_i_is_1027811366364555365",
    "affiliate_url": "https://hb.afl.rakuten.co.jp/hgc/g00r1fdj.f7sle73b.g00r1fdj.f7slf83a/?pc=https%3A%2F%2Fitem.rakuten.co.jp%2Flcs-live%2F10016929%2F&m=http%3A%2F%2Fm.rakuten.co.jp%2Flcs-live%2Fi%2F10016842%2F&rafcid=wsc_i_is_1027811366364555365",
    "timestamp": "2025-08-25 09:43:39"
  },
  {
    "jan_code": "4974019499352",
    "product_name": "シャープ AQUOSサウンドパートナー AN-SS3-B [ブラック] JAN 4974019499352",
    "current_price": 19819,
    "previous_price": 25740.0,
    "price_change_rate": -23.003108003108004,
    "current_availability": "在庫あり",
    "previous_availability": "在庫あり",
    "shop_name": "アークマーケット",
    "item_url": "https://hb.afl.rakuten.co.jp/hgc/g00t9goj.f7sleafb.g00t9goj.f7slfab2/?pc=https%3A%2F%2Fitem.rakuten.co.jp%2Farc-market-kaden%2F4974019499352%2F&m=http%3A%2F%2Fm.rakuten.co.jp%2Farc-market-kaden%2Fi%2F10011276%2F&rafcid=wsc_i_is_1027811366364555365",
    "affiliate_url": "https://hb.afl.rakuten.co.jp/hgc/g00t9goj.f7sleafb.g00t9goj.f7slfab2/?pc=https%3A%2F%2Fitem.rakuten.co.jp%2Farc-market-kaden%2F4974019499352%2F&m=http%3A%2F%2Fm.rakuten.co.jp%2Farc-market-kaden%2Fi%2F10011276%2F&rafcid=wsc_i_is_1027811366364555365",
    "timestamp": "2025-08-25 09:51:30"
  },
  {
    "jan_code": "4988602176490",
    "product_name": "Nintendo Switch 桃太郎電鉄ワールド 地球は希望でまわってる！KONAMI【ネコポス便／パッケージ版】",
    "current_price": 4829,
    "previous_price": 5820.0,
    "price_change_rate": -17.027491408934708,
    "current_availability": "在庫あり",
    "previous_availability": "在庫あり",
    "shop_name": "らいぶshop",
    "item_url": "https://hb.afl.rakuten.co.jp/hgc/g00r1fdj.f7sle73b.g00r1fdj.f7slf83a/?pc=https%3A%2F%2Fitem.rakuten.co.jp%2Flcs-live%2F10014127%2F&m=http%3A%2F%2Fm.rakuten.co.jp%2Flcs-live%2Fi%2F10014115%2F&rafcid=wsc_i_is_1027811366364555365",
    "affiliate_url": "https://hb.afl.rakuten.co.jp/hgc/g00r1fdj.f7sle73b.g00r1fdj.f7slf83a/?pc=https%3A%2F%2Fitem.rakuten.co.jp%2Flcs-live%2F10014127%2F&m=http%3A%2F%2Fm.rakuten.co.jp%2Flcs-live%2Fi%2F10014115%2F&rafcid=wsc_i_is_1027811366364555365",
    "timestamp": "2025-08-25 09:56:37"
  }
]