[
  {
    "jan_code": "4549873188225",
    "product_name": "【当日出荷】日立 掃除機 紙パック式 小型・軽量ボディ&強烈パワー (ライトゴールド) CV-KP90L-N 小型 軽量ボディ 強烈パワー ライトゴールド",
    "current_price": 21500,
    "previous_price": 22800.0,
    "price_change_rate": -5.701754385964912,
    "current_availability": "在庫あり",
    "previous_availability": "在庫あり",
    "shop_name": "タンタンショップ",
    "item_url": "https://hb.afl.rakuten.co.jp/hgc/g00pme3j.f7slea8b.g00pme3j.f7slf9b9/?pc=https%3A%2F%2Fitem.rakuten.co.jp%2Ftantan%2F3172847%2F&m=http%3A%2F%2Fm.rakuten.co.jp%2Ftantan%2Fi%2F13366234%2F&rafcid=wsc_i_is_1027811366364555365",
    "affiliate_url": "https://hb.afl.rakuten.co.jp/hgc/g00pme3j.f7slea8b.g00pme3j.f7slf9b9/?pc=https%3A%2F%2Fitem.rakuten.co.jp%2Ftantan%2F3172847%2F&m=http%3A%2F%2Fm.rakuten.co.jp%2Ftantan%2Fi%2F13366234%2F&rafcid=wsc_i_is_1027811366364555365",
    "timestamp": "2025-07-11 15:28:05"
  },
  {
    "jan_code": "4550556131292",
    "product_name": "シャープ　SHARP　SIMフリースマートフォン AQUOS wish4 MediaTekTM Dimensity 700 6.6型 メモリ/ストレージ：4GB/64GB ブルー　SH-M27-A",
    "current_price": 33822,
    "previous_price": 37400.0,
    "price_change_rate": -9.566844919786096,
    "current_availability": "在庫あり",
    "previous_availability": "在庫あり",
    "shop_name": "コジマ楽天市場店",
    "item_url": "https://hb.afl.rakuten.co.jp/hgc/g00r8mvj.f7sle8e7.g00r8mvj.f7slf16c/?pc=https%3A%2F%2Fitem.rakuten.co.jp%2Fr-kojima%2F4550556131292%2F&m=http%3A%2F%2Fm.rakuten.co.jp%2Fr-kojima%2Fi%2F11507434%2F&rafcid=wsc_i_is_1027811366364555365",
    "affiliate_url": "https://hb.afl.rakuten.co.jp/hgc/g00r8mvj.f7sle8e7.g00r8mvj.f7slf16c/?pc=https%3A%2F%2Fitem.rakuten.co.jp%2Fr-kojima%2F4550556131292%2F&m=http%3A%2F%2Fm.rakuten.co.jp%2Fr-kojima%2Fi%2F11507434%2F&rafcid=wsc_i_is_1027811366364555365",
    "timestamp": "2025-07-11 15:41:53"
  },
  {
    "jan_code": "4550556144346",
    "product_name": "シャープ　SHARP　SIMフリースマートフォン AQUOS sense9 Snapdragon7s Gen2 Mobile Platform 6.1インチ メモリ/ストレージ：8GB/256GB ブルー　SHM29BA",
    "current_price": 66618,
    "previous_price": 72600.0,
    "price_change_rate": -8.239669421487603,
    "current_availability": "在庫あり",
    "previous_availability": "在庫あり",
    "shop_name": "コジマ楽天市場店",
    "item_url": "https://hb.afl.rakuten.co.jp/hgc/g00r8mvj.f7sle8e7.g00r8mvj.f7slf16c/?pc=https%3A%2F%2Fitem.rakuten.co.jp%2Fr-kojima%2F4550556144346%2F&m=http%3A%2F%2Fm.rakuten.co.jp%2Fr-kojima%2Fi%2F11549694%2F&rafcid=wsc_i_is_1027811366364555365",
    "affiliate_url": "https://hb.afl.rakuten.co.jp/hgc/g00r8mvj.f7sle8e7.g00r8mvj.f7slf16c/?pc=https%3A%2F%2Fitem.rakuten.co.jp%2Fr-kojima%2F4550556144346%2F&m=http%3A%2F%2Fm.rakuten.co.jp%2Fr-kojima%2Fi%2F11549694%2F&rafcid=wsc_i_is_1027811366364555365",
    "timestamp": "2025-07-11 15:42:13"
  },
  {
    "jan_code": "4550556144377",
    "product_name": "シャープ　SHARP　SIMフリースマートフォン AQUOS sense9 Snapdragon7s Gen2 Mobile Platform 6.1インチ メモリ/ストレージ：8GB/256GB ホワイト　SHM29BW",
    "current_price": 66618,
    "previous_price": 72600.0,
    "price_change_rate": -8.239669421487603,
    "current_availability": "在庫あり",
    "previous_availability": "在庫あり",
    "shop_name": "コジマ楽天市場店",
    "item_url": "https://hb.afl.rakuten.co.jp/hgc/g00r8mvj.f7sle8e7.g00r8mvj.f7slf16c/?pc=https%3A%2F%2Fitem.rakuten.co.jp%2Fr-kojima%2F4550556144377%2F&m=http%3A%2F%2Fm.rakuten.co.jp%2Fr-kojima%2Fi%2F11549697%2F&rafcid=wsc_i_is_1027811366364555365",
    "affiliate_url": "https://hb.afl.rakuten.co.jp/hgc/g00r8mvj.f7sle8e7.g00r8mvj.f7slf16c/?pc=https%3A%2F%2Fitem.rakuten.co.jp%2Fr-kojima%2F4550556144377%2F&m=http%3A%2F%2Fm.rakuten.co.jp%2Fr-kojima%2Fi%2F11549697%2F&rafcid=wsc_i_is_1027811366364555365",
    "timestamp": "2025-07-11 15:42:17"
  }
]