[
  {
    "jan_code": "4549980232521",
    "product_name": "パナソニック おたっくす デジタルコードレスFAX 子機1台付き 迷惑電話対策機能搭載 シャンパンゴールド KX-PD725DL-N",
    "current_price": 43509,
    "previous_price": 46183.0,
    "price_change_rate": -5.790009310785353,
    "current_availability": "在庫あり",
    "previous_availability": "在庫あり",
    "shop_name": "MONOPARK",
    "item_url": "https://hb.afl.rakuten.co.jp/hgc/g00u3u1j.f7sle5fc.g00u3u1j.f7slf020/?pc=https%3A%2F%2Fitem.rakuten.co.jp%2Fmono-park%2F202307110648294549980232521%2F&m=http%3A%2F%2Fm.rakuten.co.jp%2Fmono-park%2Fi%2F10024772%2F&rafcid=wsc_i_is_1027811366364555365",
    "affiliate_url": "https://hb.afl.rakuten.co.jp/hgc/g00u3u1j.f7sle5fc.g00u3u1j.f7slf020/?pc=https%3A%2F%2Fitem.rakuten.co.jp%2Fmono-park%2F202307110648294549980232521%2F&m=http%3A%2F%2Fm.rakuten.co.jp%2Fmono-park%2Fi%2F10024772%2F&rafcid=wsc_i_is_1027811366364555365",
    "timestamp": "2025-06-13 01:24:25"
  },
  {
    "jan_code": "4549980502372",
    "product_name": "パナソニック メンズシェーバー ラムダッシュ 3枚刃 お風呂剃り可 黒 ES-CST2T-K",
    "current_price": 19433,
    "previous_price": 22910.0,
    "price_change_rate": -15.176778699257968,
    "current_availability": "在庫あり",
    "previous_availability": "在庫あり",
    "shop_name": "MONOPARK",
    "item_url": "https://hb.afl.rakuten.co.jp/hgc/g00u3u1j.f7sle5fc.g00u3u1j.f7slf020/?pc=https%3A%2F%2Fitem.rakuten.co.jp%2Fmono-park%2F202307102254304549980502372%2F&m=http%3A%2F%2Fm.rakuten.co.jp%2Fmono-park%2Fi%2F10024436%2F&rafcid=wsc_i_is_1027811366364555365",
    "affiliate_url": "https://hb.afl.rakuten.co.jp/hgc/g00u3u1j.f7sle5fc.g00u3u1j.f7slf020/?pc=https%3A%2F%2Fitem.rakuten.co.jp%2Fmono-park%2F202307102254304549980502372%2F&m=http%3A%2F%2Fm.rakuten.co.jp%2Fmono-park%2Fi%2F10024436%2F&rafcid=wsc_i_is_1027811366364555365",
    "timestamp": "2025-06-13 01:25:32"
  },
  {
    "jan_code": "4549995192131",
    "product_name": "イヤホン・ヘッドホン アップル / APPLE AirPods Max MGYM3J/A [ピンク] 【キャンセル不可・北海道沖縄離島配送不可】 0057-4549995192131-ds",
    "current_price": 77880,
    "previous_price": 85000.0,
    "price_change_rate": -8.376470588235293,
    "current_availability": "在庫あり",
    "previous_availability": "在庫あり",
    "shop_name": "パソコンパーツのアプライド",
    "item_url": "https://hb.afl.rakuten.co.jp/hgc/g00pvr0j.f7sled3c.g00pvr0j.f7slfefb/?pc=https%3A%2F%2Fitem.rakuten.co.jp%2Fapplied2%2F4549995192131-ds%2F&m=http%3A%2F%2Fm.rakuten.co.jp%2Fapplied2%2Fi%2F11761912%2F&rafcid=wsc_i_is_1027811366364555365",
    "affiliate_url": "https://hb.afl.rakuten.co.jp/hgc/g00pvr0j.f7sled3c.g00pvr0j.f7slfefb/?pc=https%3A%2F%2Fitem.rakuten.co.jp%2Fapplied2%2F4549995192131-ds%2F&m=http%3A%2F%2Fm.rakuten.co.jp%2Fapplied2%2Fi%2F11761912%2F&rafcid=wsc_i_is_1027811366364555365",
    "timestamp": "2025-06-13 01:29:07"
  },
  {
    "jan_code": "4571591626192",
    "product_name": "Lenovo レノボ Tab M10 (3rd Gen) ZAAE0009JP [ タブレットPC ]",
    "current_price": 46000,
    "previous_price": 53361.0,
    "price_change_rate": -13.794718989524185,
    "current_availability": "在庫あり",
    "previous_availability": "在庫あり",
    "shop_name": "Trend Item Shop",
    "item_url": "https://hb.afl.rakuten.co.jp/hgc/g00u2g5j.f7sle928.g00u2g5j.f7slf396/?pc=https%3A%2F%2Fitem.rakuten.co.jp%2Ftrenditemshop%2Fb0c9lnpb92%2F&m=http%3A%2F%2Fm.rakuten.co.jp%2Ftrenditemshop%2Fi%2F10061359%2F&rafcid=wsc_i_is_1027811366364555365",
    "affiliate_url": "https://hb.afl.rakuten.co.jp/hgc/g00u2g5j.f7sle928.g00u2g5j.f7slf396/?pc=https%3A%2F%2Fitem.rakuten.co.jp%2Ftrenditemshop%2Fb0c9lnpb92%2F&m=http%3A%2F%2Fm.rakuten.co.jp%2Ftrenditemshop%2Fi%2F10061359%2F&rafcid=wsc_i_is_1027811366364555365",
    "timestamp": "2025-06-13 01:40:42"
  },
  {
    "jan_code": "4710483941733",
    "product_name": "ASROCK　グラフィックボード Radeon RX 7900 XTX Phantom Gaming 24G OC ［Radeon RXシリーズ /24GB］　RX7900XTXPG24GO",
    "current_price": 122244,
    "previous_price": 131317.0,
    "price_change_rate": -6.909234904848573,
    "current_availability": "在庫あり",
    "previous_availability": "在庫あり",
    "shop_name": "コジマ楽天市場店",
    "item_url": "https://hb.afl.rakuten.co.jp/hgc/g00r8mvj.f7sle8e7.g00r8mvj.f7slf16c/?pc=https%3A%2F%2Fitem.rakuten.co.jp%2Fr-kojima%2F4710483941733%2F&m=http%3A%2F%2Fm.rakuten.co.jp%2Fr-kojima%2Fi%2F11551164%2F&rafcid=wsc_i_is_1027811366364555365",
    "affiliate_url": "https://hb.afl.rakuten.co.jp/hgc/g00r8mvj.f7sle8e7.g00r8mvj.f7slf16c/?pc=https%3A%2F%2Fitem.rakuten.co.jp%2Fr-kojima%2F4710483941733%2F&m=http%3A%2F%2Fm.rakuten.co.jp%2Fr-kojima%2Fi%2F11551164%2F&rafcid=wsc_i_is_1027811366364555365",
    "timestamp": "2025-06-13 01:44:03"
  },
  {
    "jan_code": "4988755059411",
    "product_name": "NVIDIA GeForce RTX3060Ti 搭載 グラフィックボード GDDR6 8GB GALAKURO GAMINGシリーズ GG-RTX3060Ti-E8GB/DF/LHR",
    "current_price": 96481,
    "previous_price": 102810.0,
    "price_change_rate": -6.156015951755666,
    "current_availability": "在庫あり",
    "previous_availability": "在庫あり",
    "shop_name": "kokolohasstyle",
    "item_url": "https://hb.afl.rakuten.co.jp/hgc/g00u3xuj.f7slef54.g00u3xuj.f7slf7ae/?pc=https%3A%2F%2Fitem.rakuten.co.jp%2Fkokolohas-style%2F202307031755014988755059411%2F&m=http%3A%2F%2Fm.rakuten.co.jp%2Fkokolohas-style%2Fi%2F10049195%2F&rafcid=wsc_i_is_1027811366364555365",
    "affiliate_url": "https://hb.afl.rakuten.co.jp/hgc/g00u3xuj.f7slef54.g00u3xuj.f7slf7ae/?pc=https%3A%2F%2Fitem.rakuten.co.jp%2Fkokolohas-style%2F202307031755014988755059411%2F&m=http%3A%2F%2Fm.rakuten.co.jp%2Fkokolohas-style%2Fi%2F10049195%2F&rafcid=wsc_i_is_1027811366364555365",
    "timestamp": "2025-06-13 02:01:02"
  }
]