[
  {
    "jan_code": "4974019230023",
    "product_name": "【土日祝発送】【新品】SHARP シャープ ドライヤー プラズマクラスタードレープフロー beaute A IB-WX3-N リネンゴールド",
    "current_price": 13969,
    "previous_price": 14920.0,
    "price_change_rate": -6.373994638069705,
    "current_availability": "在庫あり",
    "previous_availability": "在庫あり",
    "shop_name": "電子問屋 2号店",
    "item_url": "https://hb.afl.rakuten.co.jp/hgc/g00u7o7j.f7sled45.g00u7o7j.f7slf662/?pc=https%3A%2F%2Fitem.rakuten.co.jp%2Furiurishop%2F4974019230023%2F&m=http%3A%2F%2Fm.rakuten.co.jp%2Furiurishop%2Fi%2F10002483%2F&rafcid=wsc_i_is_1027811366364555365",
    "affiliate_url": "https://hb.afl.rakuten.co.jp/hgc/g00u7o7j.f7sled45.g00u7o7j.f7slf662/?pc=https%3A%2F%2Fitem.rakuten.co.jp%2Furiurishop%2F4974019230023%2F&m=http%3A%2F%2Fm.rakuten.co.jp%2Furiurishop%2Fi%2F10002483%2F&rafcid=wsc_i_is_1027811366364555365",
    "timestamp": "2025-07-03 07:06:26"
  }
]