[
  {
    "jan_code": "4549873195681",
    "product_name": "◆新品未開封品◆日立 炊飯器 5.5合 圧力&スチームIH ふっくら御膳 RZ-V100HM-W フロストホワイト 日本製 大火力 沸騰鉄釜 蒸気カット◆4549873195681◆",
    "current_price": 42000,
    "previous_price": 56850.0,
    "price_change_rate": -26.121372031662272,
    "current_availability": "在庫あり",
    "previous_availability": "在庫あり",
    "shop_name": "ジョイントカンパニー",
    "item_url": "https://hb.afl.rakuten.co.jp/hgc/g00uqy9j.f7sle40f.g00uqy9j.f7slf053/?pc=https%3A%2F%2Fitem.rakuten.co.jp%2Fjoint111%2Fcompass1756493068%2F&m=http%3A%2F%2Fm.rakuten.co.jp%2Fjoint111%2Fi%2F10000224%2F&rafcid=wsc_i_is_1027811366364555365",
    "affiliate_url": "https://hb.afl.rakuten.co.jp/hgc/g00uqy9j.f7sle40f.g00uqy9j.f7slf053/?pc=https%3A%2F%2Fitem.rakuten.co.jp%2Fjoint111%2Fcompass1756493068%2F&m=http%3A%2F%2Fm.rakuten.co.jp%2Fjoint111%2Fi%2F10000224%2F&rafcid=wsc_i_is_1027811366364555365",
    "timestamp": "2025-08-29 21:16:31"
  },
  {
    "jan_code": "4549980682081",
    "product_name": "パナソニック 掃除機 コードレス 軽量 スティック サイクロン ホワイト MC-SB33J-W 送料無料",
    "current_price": 34500,
    "previous_price": 36722.0,
    "price_change_rate": -6.0508686890692225,
    "current_availability": "在庫あり",
    "previous_availability": "在庫あり",
    "shop_name": "GR　ONLINE STORE",
    "item_url": "https://hb.afl.rakuten.co.jp/hgc/g00u3i4j.f7slec59.g00u3i4j.f7slf978/?pc=https%3A%2F%2Fitem.rakuten.co.jp%2Fgr-online%2Fooc7df924338%2F&m=http%3A%2F%2Fm.rakuten.co.jp%2Fgr-online%2Fi%2F10056603%2F&rafcid=wsc_i_is_1027811366364555365",
    "affiliate_url": "https://hb.afl.rakuten.co.jp/hgc/g00u3i4j.f7slec59.g00u3i4j.f7slf978/?pc=https%3A%2F%2Fitem.rakuten.co.jp%2Fgr-online%2Fooc7df924338%2F&m=http%3A%2F%2Fm.rakuten.co.jp%2Fgr-online%2Fi%2F10056603%2F&rafcid=wsc_i_is_1027811366364555365",
    "timestamp": "2025-08-29 21:19:41"
  }
]