[
  {
    "jan_code": "4942857239119",
    "product_name": "＼レビュー特典あり／未使用｜arrows We2 F-52E｜Sランク｜SIMフリー｜保証期間180日｜富士通 FUJITSU FCNT スマホ 本体｜スマホとタブレット通販のReYuuストア(リユーストア)",
    "current_price": 17800,
    "previous_price": 19489.0,
    "price_change_rate": -8.66642721535225,
    "current_availability": "在庫あり",
    "previous_availability": "在庫あり",
    "shop_name": "ReYuuストア楽天市場店",
    "item_url": "https://hb.afl.rakuten.co.jp/hgc/g00r8kfj.f7sle295.g00r8kfj.f7slf660/?pc=https%3A%2F%2Fitem.rakuten.co.jp%2Fe-booom%2F702779%2F&m=http%3A%2F%2Fm.rakuten.co.jp%2Fe-booom%2Fi%2F10072862%2F&rafcid=wsc_i_is_1027811366364555365",
    "affiliate_url": "https://hb.afl.rakuten.co.jp/hgc/g00r8kfj.f7sle295.g00r8kfj.f7slf660/?pc=https%3A%2F%2Fitem.rakuten.co.jp%2Fe-booom%2F702779%2F&m=http%3A%2F%2Fm.rakuten.co.jp%2Fe-booom%2Fi%2F10072862%2F&rafcid=wsc_i_is_1027811366364555365",
    "timestamp": "2025-08-18 21:33:14"
  }
]