[
  {
    "jan_code": "4942857222029",
    "product_name": "新品・未使用　SIMフリー スマートフォン本体 docomo arrows We F-51B パープル スマホ本体",
    "current_price": 23688,
    "previous_price": 26805.0,
    "price_change_rate": -11.628427532176833,
    "current_availability": "在庫あり",
    "previous_availability": "在庫あり",
    "shop_name": "ショップあまのとり",
    "item_url": "https://hb.afl.rakuten.co.jp/hgc/g00trvrj.f7sle5e5.g00trvrj.f7slfb5f/?pc=https%3A%2F%2Fitem.rakuten.co.jp%2Fshop-amanotori%2F202408230829324942857222029%2F&m=http%3A%2F%2Fm.rakuten.co.jp%2Fshop-amanotori%2Fi%2F10034559%2F&rafcid=wsc_i_is_1027811366364555365",
    "affiliate_url": "https://hb.afl.rakuten.co.jp/hgc/g00trvrj.f7sle5e5.g00trvrj.f7slfb5f/?pc=https%3A%2F%2Fitem.rakuten.co.jp%2Fshop-amanotori%2F202408230829324942857222029%2F&m=http%3A%2F%2Fm.rakuten.co.jp%2Fshop-amanotori%2Fi%2F10034559%2F&rafcid=wsc_i_is_1027811366364555365",
    "timestamp": "2025-09-10 06:39:26"
  },
  {
    "jan_code": "7622100547044",
    "product_name": "【新品】IQOS イルマ i アニバーサリーモデル（ 錫セット ）※製品登録不可",
    "current_price": 14180,
    "previous_price": 18799.0,
    "price_change_rate": -24.570455875312515,
    "current_availability": "在庫あり",
    "previous_availability": "在庫あり",
    "shop_name": "ノア商社 楽天市場店",
    "item_url": "https://hb.afl.rakuten.co.jp/hgc/g00u3gvj.f7sle6e2.g00u3gvj.f7slf191/?pc=https%3A%2F%2Fitem.rakuten.co.jp%2Fnoah-shopping%2F7622100547044%2F&m=http%3A%2F%2Fm.rakuten.co.jp%2Fnoah-shopping%2Fi%2F10003108%2F&rafcid=wsc_i_is_1027811366364555365",
    "affiliate_url": "https://hb.afl.rakuten.co.jp/hgc/g00u3gvj.f7sle6e2.g00u3gvj.f7slf191/?pc=https%3A%2F%2Fitem.rakuten.co.jp%2Fnoah-shopping%2F7622100547044%2F&m=http%3A%2F%2Fm.rakuten.co.jp%2Fnoah-shopping%2Fi%2F10003108%2F&rafcid=wsc_i_is_1027811366364555365",
    "timestamp": "2025-09-10 06:56:13"
  }
]