[
  {
    "jan_code": "4548736142411",
    "product_name": "SONY ワイヤレスノイズキャンセリングステレオヘッドセット ヘッドホン WH-CH720N(B)ブラック【ラッピング対応可】 R-LOGI",
    "current_price": 14979,
    "previous_price": 17370.0,
    "price_change_rate": -13.765112262521589,
    "current_availability": "在庫あり",
    "previous_availability": "在庫あり",
    "shop_name": "MoriMoriStore（測定の森）",
    "item_url": "https://hb.afl.rakuten.co.jp/hgc/g00sxgsj.f7sledf8.g00sxgsj.f7slf301/?pc=https%3A%2F%2Fitem.rakuten.co.jp%2Fsokutei%2F4548736142411%2F&m=http%3A%2F%2Fm.rakuten.co.jp%2Fsokutei%2Fi%2F10160966%2F&rafcid=wsc_i_is_1027811366364555365",
    "affiliate_url": "https://hb.afl.rakuten.co.jp/hgc/g00sxgsj.f7sledf8.g00sxgsj.f7slf301/?pc=https%3A%2F%2Fitem.rakuten.co.jp%2Fsokutei%2F4548736142411%2F&m=http%3A%2F%2Fm.rakuten.co.jp%2Fsokutei%2Fi%2F10160966%2F&rafcid=wsc_i_is_1027811366364555365",
    "timestamp": "2025-07-09 06:26:42"
  },
  {
    "jan_code": "4549873176789",
    "product_name": "【7/10限定★抽選で2人に1人最大100%ポイントバック！要エントリー】日立【HITACHI】コードレススティッククリーナー パワーブーストサイクロン サテンブラック PV-BH900SL-K【掃除機 スタンド式充電台付き】",
    "current_price": 42130,
    "previous_price": 45380.0,
    "price_change_rate": -7.161745262230057,
    "current_availability": "在庫あり",
    "previous_availability": "在庫あり",
    "shop_name": "家電のSAKURA　楽天市場店",
    "item_url": "https://hb.afl.rakuten.co.jp/hgc/g00q4jmj.f7slea99.g00q4jmj.f7slf2ea/?pc=https%3A%2F%2Fitem.rakuten.co.jp%2Fkaden-sakura%2F4549873176789%2F&m=http%3A%2F%2Fm.rakuten.co.jp%2Fkaden-sakura%2Fi%2F10153196%2F&rafcid=wsc_i_is_1027811366364555365",
    "affiliate_url": "https://hb.afl.rakuten.co.jp/hgc/g00q4jmj.f7slea99.g00q4jmj.f7slf2ea/?pc=https%3A%2F%2Fitem.rakuten.co.jp%2Fkaden-sakura%2F4549873176789%2F&m=http%3A%2F%2Fm.rakuten.co.jp%2Fkaden-sakura%2Fi%2F10153196%2F&rafcid=wsc_i_is_1027811366364555365",
    "timestamp": "2025-07-09 06:34:11"
  },
  {
    "jan_code": "4549980694367",
    "product_name": "パナソニック 15V型 ハイビジョン ポータブル 液晶テレビ プライベート ビエラ 防水タイプ ブラック UN-15S11",
    "current_price": 74649,
    "previous_price": 82467.0,
    "price_change_rate": -9.480155698643093,
    "current_availability": "在庫あり",
    "previous_availability": "在庫あり",
    "shop_name": "ショップあまのとり",
    "item_url": "https://hb.afl.rakuten.co.jp/hgc/g00trvrj.f7sle5e5.g00trvrj.f7slfb5f/?pc=https%3A%2F%2Fitem.rakuten.co.jp%2Fshop-amanotori%2F202311131341244549980694367%2F&m=http%3A%2F%2Fm.rakuten.co.jp%2Fshop-amanotori%2Fi%2F10030901%2F&rafcid=wsc_i_is_1027811366364555365",
    "affiliate_url": "https://hb.afl.rakuten.co.jp/hgc/g00trvrj.f7sle5e5.g00trvrj.f7slfb5f/?pc=https%3A%2F%2Fitem.rakuten.co.jp%2Fshop-amanotori%2F202311131341244549980694367%2F&m=http%3A%2F%2Fm.rakuten.co.jp%2Fshop-amanotori%2Fi%2F10030901%2F&rafcid=wsc_i_is_1027811366364555365",
    "timestamp": "2025-07-09 06:37:23"
  },
  {
    "jan_code": "4549995128659",
    "product_name": "Apple アップル TV 4K 32GB MXGY2J/A 4549995128659",
    "current_price": 18000,
    "previous_price": 22800.0,
    "price_change_rate": -21.052631578947366,
    "current_availability": "在庫あり",
    "previous_availability": "在庫あり",
    "shop_name": "快適ネットショップ",
    "item_url": "https://hb.afl.rakuten.co.jp/hgc/g00u1l9j.f7sle307.g00u1l9j.f7slf2ae/?pc=https%3A%2F%2Fitem.rakuten.co.jp%2Fkaitekinetshop%2Fcompass-mxgy2ja%2F&m=http%3A%2F%2Fm.rakuten.co.jp%2Fkaitekinetshop%2Fi%2F10011236%2F&rafcid=wsc_i_is_1027811366364555365",
    "affiliate_url": "https://hb.afl.rakuten.co.jp/hgc/g00u1l9j.f7sle307.g00u1l9j.f7slf2ae/?pc=https%3A%2F%2Fitem.rakuten.co.jp%2Fkaitekinetshop%2Fcompass-mxgy2ja%2F&m=http%3A%2F%2Fm.rakuten.co.jp%2Fkaitekinetshop%2Fi%2F10011236%2F&rafcid=wsc_i_is_1027811366364555365",
    "timestamp": "2025-07-09 06:38:34"
  },
  {
    "jan_code": "4549995556452",
    "product_name": "【未使用】Apple 【Wi-Fi】 13インチ iPad Air（M3/2025) 1TB スターライト MCQ24J/A【仙台イービーンズ】保証期間6ヶ月",
    "current_price": 192980,
    "previous_price": 224455.0,
    "price_change_rate": -14.022855360762737,
    "current_availability": "在庫あり",
    "previous_availability": "在庫あり",
    "shop_name": "じゃんぱら楽天市場店",
    "item_url": "https://hb.afl.rakuten.co.jp/hgc/g00tw8sj.f7sleed1.g00tw8sj.f7slf9af/?pc=https%3A%2F%2Fitem.rakuten.co.jp%2Fjanpara%2F223030170-223%2F&m=http%3A%2F%2Fm.rakuten.co.jp%2Fjanpara%2Fi%2F10433802%2F&rafcid=wsc_i_is_1027811366364555365",
    "affiliate_url": "https://hb.afl.rakuten.co.jp/hgc/g00tw8sj.f7sleed1.g00tw8sj.f7slf9af/?pc=https%3A%2F%2Fitem.rakuten.co.jp%2Fjanpara%2F223030170-223%2F&m=http%3A%2F%2Fm.rakuten.co.jp%2Fjanpara%2Fi%2F10433802%2F&rafcid=wsc_i_is_1027811366364555365",
    "timestamp": "2025-07-09 06:46:39"
  },
  {
    "jan_code": "4580527850822",
    "product_name": "【新品・送料無料・在庫あり】FCNT arrows We2 M07 楽天モバイル版 [ライトブルー] ／ 白ロム／SIMフリー",
    "current_price": 13999,
    "previous_price": 17734.0,
    "price_change_rate": -21.06123829931206,
    "current_availability": "在庫あり",
    "previous_availability": "在庫あり",
    "shop_name": "らいぶshop",
    "item_url": "https://hb.afl.rakuten.co.jp/hgc/g00r1fdj.f7sle73b.g00r1fdj.f7slf83a/?pc=https%3A%2F%2Fitem.rakuten.co.jp%2Flcs-live%2F10018144%2F&m=http%3A%2F%2Fm.rakuten.co.jp%2Flcs-live%2Fi%2F10018040%2F&rafcid=wsc_i_is_1027811366364555365",
    "affiliate_url": "https://hb.afl.rakuten.co.jp/hgc/g00r1fdj.f7sle73b.g00r1fdj.f7slf83a/?pc=https%3A%2F%2Fitem.rakuten.co.jp%2Flcs-live%2F10018144%2F&m=http%3A%2F%2Fm.rakuten.co.jp%2Flcs-live%2Fi%2F10018040%2F&rafcid=wsc_i_is_1027811366364555365",
    "timestamp": "2025-07-09 06:50:17"
  },
  {
    "jan_code": "4942857221015",
    "product_name": "新品・未使用 docomo Galaxy A22 5G ブラック SIMフリー スマホ本体 スマートフォン本体",
    "current_price": 23415,
    "previous_price": 25493.0,
    "price_change_rate": -8.151257207860981,
    "current_availability": "在庫あり",
    "previous_availability": "在庫あり",
    "shop_name": "ショップあまのとり",
    "item_url": "https://hb.afl.rakuten.co.jp/hgc/g00trvrj.f7sle5e5.g00trvrj.f7slfb5f/?pc=https%3A%2F%2Fitem.rakuten.co.jp%2Fshop-amanotori%2F202205072342454942857221015%2F&m=http%3A%2F%2Fm.rakuten.co.jp%2Fshop-amanotori%2Fi%2F10020197%2F&rafcid=wsc_i_is_1027811366364555365",
    "affiliate_url": "https://hb.afl.rakuten.co.jp/hgc/g00trvrj.f7sle5e5.g00trvrj.f7slfb5f/?pc=https%3A%2F%2Fitem.rakuten.co.jp%2Fshop-amanotori%2F202205072342454942857221015%2F&m=http%3A%2F%2Fm.rakuten.co.jp%2Fshop-amanotori%2Fi%2F10020197%2F&rafcid=wsc_i_is_1027811366364555365",
    "timestamp": "2025-07-09 06:54:56"
  },
  {
    "jan_code": "4943765060857",
    "product_name": "【ポイント10倍】 ロジクール ヘッドセット G PRO X 2 LIGHTSPEED G-PHS-005WLWH [ホワイト] [ヘッドホンタイプ：オーバーヘッド プラグ形状：ミニプラグ 装着タイプ：両耳用 接続方式：ワイヤレス/ワイヤード(有線) リモコン：○ ゲーミング：○] 【P10倍】",
    "current_price": 50050,
    "previous_price": 55220.0,
    "price_change_rate": -9.362549800796813,
    "current_availability": "在庫あり",
    "previous_availability": "在庫あり",
    "shop_name": "YOUPLAN",
    "item_url": "https://hb.afl.rakuten.co.jp/hgc/g00rfb2j.f7sle8cc.g00rfb2j.f7slfa8f/?pc=https%3A%2F%2Fitem.rakuten.co.jp%2Fyouplan%2F100007149574%2F&m=http%3A%2F%2Fm.rakuten.co.jp%2Fyouplan%2Fi%2F10331066%2F&rafcid=wsc_i_is_1027811366364555365",
    "affiliate_url": "https://hb.afl.rakuten.co.jp/hgc/g00rfb2j.f7sle8cc.g00rfb2j.f7slfa8f/?pc=https%3A%2F%2Fitem.rakuten.co.jp%2Fyouplan%2F100007149574%2F&m=http%3A%2F%2Fm.rakuten.co.jp%2Fyouplan%2Fi%2F10331066%2F&rafcid=wsc_i_is_1027811366364555365",
    "timestamp": "2025-07-09 06:56:12"
  },
  {
    "jan_code": "6934177798917",
    "product_name": "シャオミ(Xiaomi) タブレット Redmi Pad 3GB+64GB 日本語版 10.61インチディスプレ wi-fiモデル Dolby Atmos 対応 18W急速充電 8,000mAh大容量バッテリー 軽量 ムーンライトシルバー",
    "current_price": 34862,
    "previous_price": 37986.0,
    "price_change_rate": -8.224082556731426,
    "current_availability": "在庫あり",
    "previous_availability": "在庫あり",
    "shop_name": "kokolohasstyle",
    "item_url": "https://hb.afl.rakuten.co.jp/hgc/g00u3xuj.f7slef54.g00u3xuj.f7slf7ae/?pc=https%3A%2F%2Fitem.rakuten.co.jp%2Fkokolohas-style%2F202307042102556934177798917%2F&m=http%3A%2F%2Fm.rakuten.co.jp%2Fkokolohas-style%2Fi%2F10049380%2F&rafcid=wsc_i_is_1027811366364555365",
    "affiliate_url": "https://hb.afl.rakuten.co.jp/hgc/g00u3xuj.f7slef54.g00u3xuj.f7slf7ae/?pc=https%3A%2F%2Fitem.rakuten.co.jp%2Fkokolohas-style%2F202307042102556934177798917%2F&m=http%3A%2F%2Fm.rakuten.co.jp%2Fkokolohas-style%2Fi%2F10049380%2F&rafcid=wsc_i_is_1027811366364555365",
    "timestamp": "2025-07-09 07:08:46"
  }
]