[
  {
    "jan_code": "4549995489057",
    "product_name": "【新品/取寄品】Apple iPad Pro 13インチ Wi-Fi 2TB Nano-textureディスプレイガラス搭載 2024年春モデル MWRJ3J/A シルバー アップル アイパッドプロ",
    "current_price": 328216,
    "previous_price": 358000.0,
    "price_change_rate": -8.319553072625698,
    "current_availability": "在庫あり",
    "previous_availability": "在庫あり",
    "shop_name": "Outlet Plaza",
    "item_url": "https://hb.afl.rakuten.co.jp/hgc/g00pm32j.f7sle619.g00pm32j.f7slfeb1/?pc=https%3A%2F%2Fitem.rakuten.co.jp%2Foutletplaza%2F40001054296%2F&m=http%3A%2F%2Fm.rakuten.co.jp%2Foutletplaza%2Fi%2F11396900%2F&rafcid=wsc_i_is_1027811366364555365",
    "affiliate_url": "https://hb.afl.rakuten.co.jp/hgc/g00pm32j.f7sle619.g00pm32j.f7slfeb1/?pc=https%3A%2F%2Fitem.rakuten.co.jp%2Foutletplaza%2F40001054296%2F&m=http%3A%2F%2Fm.rakuten.co.jp%2Foutletplaza%2Fi%2F11396900%2F&rafcid=wsc_i_is_1027811366364555365",
    "timestamp": "2025-08-15 03:48:54"
  }
]