[
  {
    "jan_code": "4974019133560",
    "product_name": "シャープ　SHARP　単機能電子レンジ［18L／ターンテーブル式］　RE-TM18-B",
    "current_price": 11069,
    "previous_price": 14759.0,
    "price_change_rate": -25.0016938816993,
    "current_availability": "在庫あり",
    "previous_availability": "在庫あり",
    "shop_name": "コジマ楽天市場店",
    "item_url": "https://hb.afl.rakuten.co.jp/hgc/g00r8mvj.f7sle8e7.g00r8mvj.f7slf16c/?pc=https%3A%2F%2Fitem.rakuten.co.jp%2Fr-kojima%2F4974019133560%2F&m=http%3A%2F%2Fm.rakuten.co.jp%2Fr-kojima%2Fi%2F10883867%2F&rafcid=wsc_i_is_1027811366364555365",
    "affiliate_url": "https://hb.afl.rakuten.co.jp/hgc/g00r8mvj.f7sle8e7.g00r8mvj.f7slf16c/?pc=https%3A%2F%2Fitem.rakuten.co.jp%2Fr-kojima%2F4974019133560%2F&m=http%3A%2F%2Fm.rakuten.co.jp%2Fr-kojima%2Fi%2F10883867%2F&rafcid=wsc_i_is_1027811366364555365",
    "timestamp": "2025-07-22 18:39:58"
  },
  {
    "jan_code": "6970214572065",
    "product_name": "[ジャンク] Pico(ピコ) PICO4 128GB VRヘッドセットpico4-128 [難あり(D)]",
    "current_price": 32800,
    "previous_price": 87632.0,
    "price_change_rate": -62.57075041080884,
    "current_availability": "在庫あり",
    "previous_availability": "在庫あり",
    "shop_name": "レンティオ アウトレット",
    "item_url": "https://hb.afl.rakuten.co.jp/hgc/g00tqlcj.f7sle11d.g00tqlcj.f7slf166/?pc=https%3A%2F%2Fitem.rakuten.co.jp%2Foutl%2Frc_itfdquihgo1a_ce63%2F&m=http%3A%2F%2Fm.rakuten.co.jp%2Foutl%2Fi%2F10009710%2F&rafcid=wsc_i_is_1027811366364555365",
    "affiliate_url": "https://hb.afl.rakuten.co.jp/hgc/g00tqlcj.f7sle11d.g00tqlcj.f7slf166/?pc=https%3A%2F%2Fitem.rakuten.co.jp%2Foutl%2Frc_itfdquihgo1a_ce63%2F&m=http%3A%2F%2Fm.rakuten.co.jp%2Foutl%2Fi%2F10009710%2F&rafcid=wsc_i_is_1027811366364555365",
    "timestamp": "2025-07-22 18:48:32"
  }
]