[
  {
    "jan_code": "4549980783450",
    "product_name": "Panasonic パナソニック 掃除機 MC-PJ230G-W 紙パック式 ホワイト 軽量コンパクト クリーンセンサー搭載",
    "current_price": 33080,
    "previous_price": 37750.0,
    "price_change_rate": -12.370860927152318,
    "current_availability": "在庫あり",
    "previous_availability": "在庫あり",
    "shop_name": "クラウンMARKET",
    "item_url": "https://hb.afl.rakuten.co.jp/hgc/g00t5nnj.f7sle607.g00t5nnj.f7slf7e7/?pc=https%3A%2F%2Fitem.rakuten.co.jp%2Fvictoryslife%2F0615-019637%2F&m=http%3A%2F%2Fm.rakuten.co.jp%2Fvictoryslife%2Fi%2F10008264%2F&rafcid=wsc_i_is_1027811366364555365",
    "affiliate_url": "https://hb.afl.rakuten.co.jp/hgc/g00t5nnj.f7sle607.g00t5nnj.f7slf7e7/?pc=https%3A%2F%2Fitem.rakuten.co.jp%2Fvictoryslife%2F0615-019637%2F&m=http%3A%2F%2Fm.rakuten.co.jp%2Fvictoryslife%2Fi%2F10008264%2F&rafcid=wsc_i_is_1027811366364555365",
    "timestamp": "2025-06-22 01:34:05"
  },
  {
    "jan_code": "4549995208351",
    "product_name": "【訳あり】Apple MagSafe充電器 / MHXH3AM/A アップル純正 / 日本国内正規品 4549995208351",
    "current_price": 6632,
    "previous_price": 7674.0,
    "price_change_rate": -13.578316393015378,
    "current_availability": "在庫あり",
    "previous_availability": "在庫あり",
    "shop_name": "RELUCIR楽天市場店",
    "item_url": "https://hb.afl.rakuten.co.jp/hgc/g00uhpej.f7sle874.g00uhpej.f7slf293/?pc=https%3A%2F%2Fitem.rakuten.co.jp%2Frelucir%2F4549995208351%2F&m=http%3A%2F%2Fm.rakuten.co.jp%2Frelucir%2Fi%2F10002013%2F&rafcid=wsc_i_is_1027811366364555365",
    "affiliate_url": "https://hb.afl.rakuten.co.jp/hgc/g00uhpej.f7sle874.g00uhpej.f7slf293/?pc=https%3A%2F%2Fitem.rakuten.co.jp%2Frelucir%2F4549995208351%2F&m=http%3A%2F%2Fm.rakuten.co.jp%2Frelucir%2Fi%2F10002013%2F&rafcid=wsc_i_is_1027811366364555365",
    "timestamp": "2025-06-22 01:34:43"
  }
]