[
  {
    "jan_code": "4549995250367",
    "product_name": "「新品」iPad mini 8.3インチ 第6世代 Wi-Fi+Cellular 64GB 2021年秋モデル MK893J/A SIMフリー [スペースグレイ]【即納】【あす楽】【プレゼント】",
    "current_price": 84240,
    "previous_price": 89130.0,
    "price_change_rate": -5.486368226186469,
    "current_availability": "在庫あり",
    "previous_availability": "在庫あり",
    "shop_name": "家電問屋　楽天市場店",
    "item_url": "https://hb.afl.rakuten.co.jp/hgc/g00trgdj.f7sle9ba.g00trgdj.f7slf6f0/?pc=https%3A%2F%2Fitem.rakuten.co.jp%2Ficockaden%2Fmk893ja%2F&m=http%3A%2F%2Fm.rakuten.co.jp%2Ficockaden%2Fi%2F10005057%2F&rafcid=wsc_i_is_1027811366364555365",
    "affiliate_url": "https://hb.afl.rakuten.co.jp/hgc/g00trgdj.f7sle9ba.g00trgdj.f7slf6f0/?pc=https%3A%2F%2Fitem.rakuten.co.jp%2Ficockaden%2Fmk893ja%2F&m=http%3A%2F%2Fm.rakuten.co.jp%2Ficockaden%2Fi%2F10005057%2F&rafcid=wsc_i_is_1027811366364555365",
    "timestamp": "2025-04-09 13:55:34"
  },
  {
    "jan_code": "4549995556391",
    "product_name": "【新品】iPad Air 13インチ Wi-Fi 512GB 2025年春モデル MCNT4J/A スペースグレイ",
    "current_price": 171969,
    "previous_price": 186000.0,
    "price_change_rate": -7.543548387096774,
    "current_availability": "在庫あり",
    "previous_availability": "在庫あり",
    "shop_name": "電子問屋ワールドいち",
    "item_url": "https://hb.afl.rakuten.co.jp/hgc/g00r2muj.f7sle76b.g00r2muj.f7slff29/?pc=https%3A%2F%2Fitem.rakuten.co.jp%2Fauc-worldichi%2F4549995556391%2F&m=http%3A%2F%2Fm.rakuten.co.jp%2Fauc-worldichi%2Fi%2F10028191%2F&rafcid=wsc_i_is_1027811366364555365",
    "affiliate_url": "https://hb.afl.rakuten.co.jp/hgc/g00r2muj.f7sle76b.g00r2muj.f7slff29/?pc=https%3A%2F%2Fitem.rakuten.co.jp%2Fauc-worldichi%2F4549995556391%2F&m=http%3A%2F%2Fm.rakuten.co.jp%2Fauc-worldichi%2Fi%2F10028191%2F&rafcid=wsc_i_is_1027811366364555365",
    "timestamp": "2025-04-09 14:03:15"
  },
  {
    "jan_code": "4974305220226",
    "product_name": "【新品】ZOJIRUSHI 象印 炊飯器 極め炊き NW-JX10-BA ブラック",
    "current_price": 35969,
    "previous_price": 39600.0,
    "price_change_rate": -9.169191919191919,
    "current_availability": "在庫あり",
    "previous_availability": "在庫あり",
    "shop_name": "電子問屋ワールドいち",
    "item_url": "https://hb.afl.rakuten.co.jp/hgc/g00r2muj.f7sle76b.g00r2muj.f7slff29/?pc=https%3A%2F%2Fitem.rakuten.co.jp%2Fauc-worldichi%2F4974305220226%2F&m=http%3A%2F%2Fm.rakuten.co.jp%2Fauc-worldichi%2Fi%2F10014338%2F&rafcid=wsc_i_is_1027811366364555365",
    "affiliate_url": "https://hb.afl.rakuten.co.jp/hgc/g00r2muj.f7sle76b.g00r2muj.f7slff29/?pc=https%3A%2F%2Fitem.rakuten.co.jp%2Fauc-worldichi%2F4974305220226%2F&m=http%3A%2F%2Fm.rakuten.co.jp%2Fauc-worldichi%2Fi%2F10014338%2F&rafcid=wsc_i_is_1027811366364555365",
    "timestamp": "2025-04-09 14:20:38"
  },
  {
    "jan_code": "4981254066553",
    "product_name": "BUFFALO　無線LANルーター　AirStation WXR-11000XE12 [チタニウムグレー]",
    "current_price": 37480,
    "previous_price": 45533.0,
    "price_change_rate": -17.6860738365581,
    "current_availability": "在庫あり",
    "previous_availability": "在庫あり",
    "shop_name": "ウインクデジタル　楽天市場店",
    "item_url": "https://hb.afl.rakuten.co.jp/hgc/g00s0brj.f7sle6f0.g00s0brj.f7slfbe8/?pc=https%3A%2F%2Fitem.rakuten.co.jp%2Fwinkstore%2F255196%2F&m=http%3A%2F%2Fm.rakuten.co.jp%2Fwinkstore%2Fi%2F10035253%2F&rafcid=wsc_i_is_1027811366364555365",
    "affiliate_url": "https://hb.afl.rakuten.co.jp/hgc/g00s0brj.f7sle6f0.g00s0brj.f7slfbe8/?pc=https%3A%2F%2Fitem.rakuten.co.jp%2Fwinkstore%2F255196%2F&m=http%3A%2F%2Fm.rakuten.co.jp%2Fwinkstore%2Fi%2F10035253%2F&rafcid=wsc_i_is_1027811366364555365",
    "timestamp": "2025-04-09 14:22:56"
  },
  {
    "jan_code": "4986773230683",
    "product_name": "【新品】SAMSUNG サムスン Galaxy Tab S9 SM-X710NZAAXJP グラファイト",
    "current_price": 109000,
    "previous_price": 122180.0,
    "price_change_rate": -10.787362907186118,
    "current_availability": "在庫あり",
    "previous_availability": "在庫あり",
    "shop_name": "電子問屋ワールドいち",
    "item_url": "https://hb.afl.rakuten.co.jp/hgc/g00r2muj.f7sle76b.g00r2muj.f7slff29/?pc=https%3A%2F%2Fitem.rakuten.co.jp%2Fauc-worldichi%2F4986773230683%2F&m=http%3A%2F%2Fm.rakuten.co.jp%2Fauc-worldichi%2Fi%2F10020195%2F&rafcid=wsc_i_is_1027811366364555365",
    "affiliate_url": "https://hb.afl.rakuten.co.jp/hgc/g00r2muj.f7sle76b.g00r2muj.f7slff29/?pc=https%3A%2F%2Fitem.rakuten.co.jp%2Fauc-worldichi%2F4986773230683%2F&m=http%3A%2F%2Fm.rakuten.co.jp%2Fauc-worldichi%2Fi%2F10020195%2F&rafcid=wsc_i_is_1027811366364555365",
    "timestamp": "2025-04-09 14:23:09"
  }
]